lidar/__init__.py
lidar/cli.py
lidar/common.py
lidar/example.py
lidar/filling.py
lidar/filtering.py
lidar/gui.py
lidar/lidar.py
lidar/mounts.py
lidar/slicing.py
lidar/data/dem.tif
lidar/data/dsm.tif
lidar/data/sink.tif
lidar-0.8.4.dist-info/LICENSE
lidar-0.8.4.dist-info/METADATA
lidar-0.8.4.dist-info/WHEEL
lidar-0.8.4.dist-info/dependency_links.txt
lidar-0.8.4.dist-info/entry_points.txt
lidar-0.8.4.dist-info/top_level.txt
lidar-0.8.4.dist-info/RECORD
