Metadata-Version: 2.2
Name: lidar
Version: 0.8.4
Summary: A Python package for delineating nested surface depressions in digital elevation data
Home-page: https://github.com/opengeos/lidar
Author: Qiusheng Wu
Author-email: giswqs@gmail.com
License: MIT license
Keywords: lidar
Classifier: Development Status :: 2 - Pre-Alpha
Classifier: Intended Audience :: Developers
Classifier: License :: OSI Approved :: MIT License
Classifier: Natural Language :: English
Classifier: Programming Language :: Python :: 3.7
Classifier: Programming Language :: Python :: 3.8
Classifier: Programming Language :: Python :: 3.9
License-File: LICENSE
Requires-Dist: Click>=6.0
Requires-Dist: gdown
Requires-Dist: geopandas
Requires-Dist: matplotlib
Requires-Dist: numpy
Requires-Dist: pandas
Requires-Dist: pyshp
Requires-Dist: scikit-image
Requires-Dist: scipy
Requires-Dist: whitebox
Provides-Extra: all
Requires-Dist: geopandas; extra == "all"
Requires-Dist: rasterio; extra == "all"
Dynamic: author
Dynamic: author-email
Dynamic: classifier
Dynamic: description
Dynamic: description-content-type
Dynamic: home-page
Dynamic: keywords
Dynamic: license
Dynamic: provides-extra
Dynamic: requires-dist
Dynamic: summary
